hrcommons/__init__.py
hr_commons-0.1.dist-info/METADATA
hr_commons-0.1.dist-info/WHEEL
hr_commons-0.1.dist-info/top_level.txt
hr_commons-0.1.dist-info/RECORD
