Metadata-Version: 2.1
Name: hr-commons
Version: 0.1
Summary: Common code for HR
Author: Joshua "jag" Ginsberg
Author-email: jag@flowtheory.net
